totp/__init__.py
totp/cli.py
totp-1.3.0.dist-info/LICENCE
totp-1.3.0.dist-info/METADATA
totp-1.3.0.dist-info/WHEEL
totp-1.3.0.dist-info/entry_points.txt
totp-1.3.0.dist-info/top_level.txt
totp-1.3.0.dist-info/RECORD
