Metadata-Version: 1.1
Name: totp
Version: 1.3.0
Summary: A cli based TOTP app.
Home-page: https://github.com/WhyNotHugo/totp-cli/
Author: Hugo Osvaldo Barrera
Author-email: hugo@barrera.io
License: ISC
Platform: UNKNOWN
Classifier: Development Status :: 4 - Beta
Classifier: Environment :: Console
Classifier: Environment :: Console :: Curses
Classifier: License :: OSI Approved :: MIT License
Classifier: Operating System :: POSIX
Classifier: Topic :: Utilities
